work_stream/__init__.py
work_stream/block.py
work_stream/branch.py
work_stream/container.py
work_stream/line.py
work_stream-0.0.2.dist-info/LICENSE
work_stream-0.0.2.dist-info/METADATA
work_stream-0.0.2.dist-info/WHEEL
work_stream-0.0.2.dist-info/top_level.txt
work_stream-0.0.2.dist-info/zip-safe
work_stream-0.0.2.dist-info/RECORD
