Metadata-Version: 2.1
Name: work-stream
Version: 0.0.2
Summary: 这是一个运维工作流模块
Home-page: https://github.com/fengqing2021/work-stream
Author: fengqing
Author-email: fq20210602@gmail.com
License: UNKNOWN
Platform: UNKNOWN
Requires-Python: >=3.6
License-File: LICENSE
